COPYING
COPYING.LESSER
periodiq.py
periodiq-0.13.0.dist-info/COPYING
periodiq-0.13.0.dist-info/COPYING.LESSER
periodiq-0.13.0.dist-info/METADATA
periodiq-0.13.0.dist-info/WHEEL
periodiq-0.13.0.dist-info/entry_points.txt
periodiq-0.13.0.dist-info/RECORD
