Metadata-Version: 2.1
Name: periodiq
Version: 0.13.0
Summary: Simple Scheduler for Dramatiq Task Queue
License: LGPL-3.0+
Author: Étienne BERSAC
Requires-Python: >=3.6,<4.0
Classifier: License :: OSI Approved :: GNU Lesser General Public License v3 or later (LGPLv3+)
Classifier: Programming Language :: Python :: 3
Classifier: Programming Language :: Python :: 3.6
Classifier: Programming Language :: Python :: 3.7
Classifier: Programming Language :: Python :: 3.8
Classifier: Programming Language :: Python :: 3.9
Classifier: Programming Language :: Python :: 3.10
Classifier: Programming Language :: Python :: 3.11
Classifier: Programming Language :: Python :: 3.12
Requires-Dist: dramatiq (>=1.5,<2.0)
Requires-Dist: pendulum (>=2.0,<4)
